[
    {
        "exitcode": 0,
        "id": "4.22",
        "known_error": 0,
        "name": "RunCosmics2011A+RunCosmics2011A+RECOCOSD+ALCACOSD+SKIMCOSD+HARVESTDC",
        "steps": [
            {
                "errors": 0,
                "status": "PASSED",
                "warnings": 0
            },
            {
                "errors": 4,
                "status": "PASSED",
                "warnings": 1275
            },
            {
                "errors": 0,
                "status": "PASSED",
                "warnings": 272
            },
            {
                "errors": 0,
                "status": "PASSED",
                "warnings": 255
            },
            {
                "errors": 72,
                "status": "PASSED",
                "warnings": 0
            }
        ]
    },
    {
        "exitcode": 0,
        "id": "136.733",
        "known_error": 0,
        "name": "RunCosmics2016B+RunCosmics2016B+RECOCOSDRUN2+ALCACOSDRUN2+HARVESTDCRUN2",
        "steps": [
            {
                "errors": 0,
                "status": "PASSED",
                "warnings": 0
            },
            {
                "errors": 2,
                "status": "PASSED",
                "warnings": 2044
            },
            {
                "errors": 0,
                "status": "PASSED",
                "warnings": 138
            },
            {
                "errors": 74,
                "status": "PASSED",
                "warnings": 0
            }
        ]
    },
    {
        "exitcode": 0,
        "id": "136.7611",
        "known_error": 0,
        "name": "RunJetHT2016E_reminiaod+RunJetHT2016E_reminiaod+REMINIAOD_data2016_HIPM+HARVESTDR2_REMINIAOD_data2016_HIPM",
        "steps": [
            {
                "errors": 0,
                "status": "PASSED",
                "warnings": 0
            },
            {
                "errors": 8,
                "status": "PASSED",
                "warnings": 537
            },
            {
                "errors": 0,
                "status": "PASSED",
                "warnings": 0
            }
        ]
    },
    {
        "exitcode": 0,
        "id": "136.7721",
        "known_error": 0,
        "name": "RunJetHT2016H_reminiaod+RunJetHT2016H_reminiaod+REMINIAOD_data2016+HARVESTDR2_REMINIAOD_data2016",
        "steps": [
            {
                "errors": 0,
                "status": "PASSED",
                "warnings": 0
            },
            {
                "errors": 8,
                "status": "PASSED",
                "warnings": 339
            },
            {
                "errors": 0,
                "status": "PASSED",
                "warnings": 0
            }
        ]
    },
    {
        "exitcode": 0,
        "id": "2017.7",
        "known_error": 0,
        "name": "H125GGgluonfusion_13_UP17+H125GGgluonfusionFS_13_UP17+HARVESTUP17FS+MINIAODMCUP17FS",
        "steps": [
            {
                "errors": 0,
                "status": "PASSED",
                "warnings": 31
            },
            {
                "errors": 3,
                "status": "PASSED",
                "warnings": 0
            },
            {
                "errors": 16,
                "status": "PASSED",
                "warnings": 119
            }
        ]
    },
    {
        "exitcode": 0,
        "id": "2017.8",
        "known_error": 0,
        "name": "MinBiasFS_13_UP17_ForMixing+MinBiasFS_13_UP17_ForMixing",
        "steps": [
            {
                "errors": 0,
                "status": "PASSED",
                "warnings": 24
            }
        ]
    },
    {
        "exitcode": 0,
        "id": "250406.0",
        "known_error": 0,
        "name": "ZMM_13+FS_ZMM_13_PRMXUP15_PU25+HARVESTUP15FS+MINIAODMCUP15FS",
        "steps": [
            {
                "errors": 0,
                "status": "PASSED",
                "warnings": 760
            },
            {
                "errors": 3,
                "status": "PASSED",
                "warnings": 0
            },
            {
                "errors": 16,
                "status": "PASSED",
                "warnings": 243
            }
        ]
    }
]
